LICENSE
MANIFEST.in
README.md
requirements.txt
setup.py
cloudquery/__init__.py
cloudquery/schema.py
cloudquery/shell.py
cloudquery/table_registry.py
cloudquery/tables_aws.py
cloudquery/vtable.py
cloudquery.egg-info/PKG-INFO
cloudquery.egg-info/SOURCES.txt
cloudquery.egg-info/dependency_links.txt
cloudquery.egg-info/entry_points.txt
cloudquery.egg-info/requires.txt
cloudquery.egg-info/top_level.txt
test/.coverage
test/test_aws.py
test/test_table_registry.py
test/test_vtable.py
test/util.py