Metadata-Version: 2.1
Name: cloudquery
Version: 0.0.1rc1
Summary: SQL interface to your cloud resources
Home-page: https://github.com/dongting/cloudquery
Author: Dongting Yu
Author-email: dongtingyu@gmail.com
License: UNKNOWN
Platform: UNKNOWN
Classifier: Programming Language :: Python :: 3
Classifier: License :: OSI Approved :: MIT License
Classifier: Operating System :: OS Independent
Requires-Python: >=3.6
